{"trial_id": "009", "hyperparameters": {"space": [{"class_name": "Int", "config": {"name": "num_layers", "default": null, "conditions": [], "min_value": 1, "max_value": 10, "step": 1, "sampling": null}}, {"class_name": "Float", "config": {"name": "dr", "default": 0.1, "conditions": [], "min_value": 0.1, "max_value": 0.5, "step": null, "sampling": null}}, {"class_name": "Float", "config": {"name": "lr", "default": 0.0001, "conditions": [], "min_value": 0.0001, "max_value": 0.01, "step": null, "sampling": "log"}}, {"class_name": "Int", "config": {"name": "units_0", "default": null, "conditions": [], "min_value": 5, "max_value": 200, "step": 10, "sampling": null}}, {"class_name": "Choice", "config": {"name": "activation_0", "default": "relu", "conditions": [], "values": ["relu", "tanh"], "ordered": false}}, {"class_name": "Int", "config": {"name": "units_1", "default": null, "conditions": [], "min_value": 5, "max_value": 200, "step": 10, "sampling": null}}, {"class_name": "Choice", "config": {"name": "activation_1", "default": "relu", "conditions": [], "values": ["relu", "tanh"], "ordered": false}}, {"class_name": "Int", "config": {"name": "units_2", "default": null, "conditions": [], "min_value": 5, "max_value": 200, "step": 10, "sampling": null}}, {"class_name": "Choice", "config": {"name": "activation_2", "default": "relu", "conditions": [], "values": ["relu", "tanh"], "ordered": false}}, {"class_name": "Int", "config": {"name": "units_3", "default": null, "conditions": [], "min_value": 5, "max_value": 200, "step": 10, "sampling": null}}, {"class_name": "Choice", "config": {"name": "activation_3", "default": "relu", "conditions": [], "values": ["relu", "tanh"], "ordered": false}}, {"class_name": "Int", "config": {"name": "units_4", "default": null, "conditions": [], "min_value": 5, "max_value": 200, "step": 10, "sampling": null}}, {"class_name": "Choice", "config": {"name": "activation_4", "default": "relu", "conditions": [], "values": ["relu", "tanh"], "ordered": false}}, {"class_name": "Int", "config": {"name": "units_5", "default": null, "conditions": [], "min_value": 5, "max_value": 200, "step": 10, "sampling": null}}, {"class_name": "Choice", "config": {"name": "activation_5", "default": "relu", "conditions": [], "values": ["relu", "tanh"], "ordered": false}}, {"class_name": "Int", "config": {"name": "units_6", "default": null, "conditions": [], "min_value": 5, "max_value": 200, "step": 10, "sampling": null}}, {"class_name": "Choice", "config": {"name": "activation_6", "default": "relu", "conditions": [], "values": ["relu", "tanh"], "ordered": false}}, {"class_name": "Int", "config": {"name": "units_7", "default": null, "conditions": [], "min_value": 5, "max_value": 200, "step": 10, "sampling": null}}, {"class_name": "Choice", "config": {"name": "activation_7", "default": "relu", "conditions": [], "values": ["relu", "tanh"], "ordered": false}}, {"class_name": "Int", "config": {"name": "units_8", "default": null, "conditions": [], "min_value": 5, "max_value": 200, "step": 10, "sampling": null}}, {"class_name": "Choice", "config": {"name": "activation_8", "default": "relu", "conditions": [], "values": ["relu", "tanh"], "ordered": false}}, {"class_name": "Int", "config": {"name": "units_9", "default": null, "conditions": [], "min_value": 5, "max_value": 200, "step": 10, "sampling": null}}, {"class_name": "Choice", "config": {"name": "activation_9", "default": "relu", "conditions": [], "values": ["relu", "tanh"], "ordered": false}}], "values": {"num_layers": 8, "dr": 0.49358406082300654, "lr": 0.001368581918321357, "units_0": 15, "activation_0": "relu", "units_1": 95, "activation_1": "tanh", "units_2": 175, "activation_2": "relu", "units_3": 195, "activation_3": "relu", "units_4": 85, "activation_4": "relu", "units_5": 115, "activation_5": "tanh", "units_6": 25, "activation_6": "tanh", "units_7": 195, "activation_7": "relu", "units_8": 85, "activation_8": "relu", "units_9": 75, "activation_9": "tanh"}}, "metrics": {"metrics": {"loss": {"direction": "min", "observations": [{"value": [0.4187821298837662], "step": 26}]}, "accuracy": {"direction": "max", "observations": [{"value": [0.8123053014278412], "step": 26}]}, "val_loss": {"direction": "min", "observations": [{"value": [0.4625502973794937], "step": 26}]}, "val_accuracy": {"direction": "max", "observations": [{"value": [0.7968299686908722], "step": 26}]}}}, "score": 0.7968299686908722, "best_step": 26, "status": "COMPLETED"}