{"trial_id": "025", "hyperparameters": {"space": [{"class_name": "Int", "config": {"name": "num_layers", "default": null, "conditions": [], "min_value": 1, "max_value": 10, "step": 1, "sampling": null}}, {"class_name": "Float", "config": {"name": "dr", "default": 0.1, "conditions": [], "min_value": 0.1, "max_value": 0.5, "step": null, "sampling": null}}, {"class_name": "Float", "config": {"name": "lr", "default": 0.0001, "conditions": [], "min_value": 0.0001, "max_value": 0.01, "step": null, "sampling": "log"}}, {"class_name": "Int", "config": {"name": "units_0", "default": null, "conditions": [], "min_value": 5, "max_value": 200, "step": 10, "sampling": null}}, {"class_name": "Choice", "config": {"name": "activation_0", "default": "relu", "conditions": [], "values": ["relu", "tanh"], "ordered": false}}, {"class_name": "Int", "config": {"name": "units_1", "default": null, "conditions": [], "min_value": 5, "max_value": 200, "step": 10, "sampling": null}}, {"class_name": "Choice", "config": {"name": "activation_1", "default": "relu", "conditions": [], "values": ["relu", "tanh"], "ordered": false}}, {"class_name": "Int", "config": {"name": "units_2", "default": null, "conditions": [], "min_value": 5, "max_value": 200, "step": 10, "sampling": null}}, {"class_name": "Choice", "config": {"name": "activation_2", "default": "relu", "conditions": [], "values": ["relu", "tanh"], "ordered": false}}, {"class_name": "Int", "config": {"name": "units_3", "default": null, "conditions": [], "min_value": 5, "max_value": 200, "step": 10, "sampling": null}}, {"class_name": "Choice", "config": {"name": "activation_3", "default": "relu", "conditions": [], "values": ["relu", "tanh"], "ordered": false}}, {"class_name": "Int", "config": {"name": "units_4", "default": null, "conditions": [], "min_value": 5, "max_value": 200, "step": 10, "sampling": null}}, {"class_name": "Choice", "config": {"name": "activation_4", "default": "relu", "conditions": [], "values": ["relu", "tanh"], "ordered": false}}, {"class_name": "Int", "config": {"name": "units_5", "default": null, "conditions": [], "min_value": 5, "max_value": 200, "step": 10, "sampling": null}}, {"class_name": "Choice", "config": {"name": "activation_5", "default": "relu", "conditions": [], "values": ["relu", "tanh"], "ordered": false}}, {"class_name": "Int", "config": {"name": "units_6", "default": null, "conditions": [], "min_value": 5, "max_value": 200, "step": 10, "sampling": null}}, {"class_name": "Choice", "config": {"name": "activation_6", "default": "relu", "conditions": [], "values": ["relu", "tanh"], "ordered": false}}, {"class_name": "Int", "config": {"name": "units_7", "default": null, "conditions": [], "min_value": 5, "max_value": 200, "step": 10, "sampling": null}}, {"class_name": "Choice", "config": {"name": "activation_7", "default": "relu", "conditions": [], "values": ["relu", "tanh"], "ordered": false}}, {"class_name": "Int", "config": {"name": "units_8", "default": null, "conditions": [], "min_value": 5, "max_value": 200, "step": 10, "sampling": null}}, {"class_name": "Choice", "config": {"name": "activation_8", "default": "relu", "conditions": [], "values": ["relu", "tanh"], "ordered": false}}, {"class_name": "Int", "config": {"name": "units_9", "default": null, "conditions": [], "min_value": 5, "max_value": 200, "step": 10, "sampling": null}}, {"class_name": "Choice", "config": {"name": "activation_9", "default": "relu", "conditions": [], "values": ["relu", "tanh"], "ordered": false}}], "values": {"num_layers": 8, "dr": 0.4559888502857644, "lr": 0.00015332259578564714, "units_0": 115, "activation_0": "tanh", "units_1": 185, "activation_1": "relu", "units_2": 85, "activation_2": "tanh", "units_3": 85, "activation_3": "relu", "units_4": 55, "activation_4": "relu", "units_5": 5, "activation_5": "relu", "units_6": 75, "activation_6": "relu", "units_7": 105, "activation_7": "tanh", "units_8": 185, "activation_8": "relu", "units_9": 125, "activation_9": "tanh"}}, "metrics": {"metrics": {"loss": {"direction": "min", "observations": [{"value": [0.6466150879859924], "step": 0}]}, "accuracy": {"direction": "max", "observations": [{"value": [0.6985981464385986], "step": 0}]}, "val_loss": {"direction": "min", "observations": [{"value": [0.661545068025589], "step": 0}]}, "val_accuracy": {"direction": "max", "observations": [{"value": [0.7636887431144714], "step": 0}]}}}, "score": 0.7636887431144714, "best_step": 0, "status": "COMPLETED"}